nr/__init__.py
nr/refreshable/__init__.py
nr/refreshable/py.typed
nr.refreshable-0.0.2.dist-info/LICENSE.txt
nr.refreshable-0.0.2.dist-info/METADATA
nr.refreshable-0.0.2.dist-info/WHEEL
nr.refreshable-0.0.2.dist-info/top_level.txt
nr.refreshable-0.0.2.dist-info/RECORD
