Metadata-Version: 2.1
Name: nr.refreshable
Version: 0.0.2
Summary: A refreshable is a simple container for a value changing over time.
Home-page: https://git.niklasrosenstein.com/NiklasRosenstein/nr
Author: Niklas Rosenstein
Author-email: rosensteinniklas@gmail.com
License: MIT
Platform: UNKNOWN
Requires-Python: >=3.4.0,<4.0.0
